fviz/__init__.py
fviz/extract.py
fviz/main.py
fviz/messagePaths.py
fviz/model/__init__.py
fviz/model/comment.py
fviz/model/comments.py
fviz/model/friend.py
fviz/model/friends.py
fviz/model/message.py
fviz/model/messages.py
fviz/model/messenger.py
fviz/model/reactedContent.py
fviz/model/reactions.py
fviz/plot/__init__.py
fviz/plot/comments.py
fviz/plot/extra.py
fviz/plot/friends.py
fviz/plot/messages.py
fviz/plot/reactions.py
fviz-1.0.0.dist-info/entry_points.txt
fviz-1.0.0.dist-info/LICENSE
fviz-1.0.0.dist-info/WHEEL
fviz-1.0.0.dist-info/METADATA
fviz-1.0.0.dist-info/RECORD
