Metadata-Version: 2.1
Name: fviz
Version: 1.0.0
Summary: fviz - Facebook data visualiser
Home-page: https://itzmeanjan.github.io/fviz
License: UNKNOWN
Author: Anjan Roy
Author-email: anjanroy@yandex.com
Requires-Python: >=3.7
Classifier: Intended Audience :: End Users/Desktop
Classifier: License :: OSI Approved :: MIT License
Classifier: Programming Language :: Python :: 3
Requires-Dist: seaborn
Requires-Dist: matplotlib
Requires-Dist: flit ; extra == "dev"
Provides-Extra: dev
